sourceknight/build.py
sourceknight/compile.py
sourceknight/context.py
sourceknight/dependencies.py
sourceknight/errors.py
sourceknight/main.py
sourceknight/state.py
sourceknight/status.py
sourceknight/unpack.py
sourceknight/update.py
sourceknight/utils.py
sourceknight/drivers/__init__.py
sourceknight/drivers/base.py
sourceknight/drivers/file.py
sourceknight/drivers/git.py
sourceknight/drivers/tar.py
sourceknight-0.3.dist-info/LICENSE
sourceknight-0.3.dist-info/METADATA
sourceknight-0.3.dist-info/WHEEL
sourceknight-0.3.dist-info/entry_points.txt
sourceknight-0.3.dist-info/top_level.txt
sourceknight-0.3.dist-info/RECORD
