Metadata-Version: 2.1
Name: sourceknight
Version: 0.3
Summary: simple dependency manager for sourcemod projects
Home-page: https://github.com/tmick0/sourceknight
Author: travis mick
Author-email: root@lo.calho.st
Requires-Python: >=3.8
License-File: LICENSE
Requires-Dist: pyyaml (<6,>=5.4)
Requires-Dist: GitPython (<4,>=3.1)
Requires-Dist: requests (<3,>=2.25)
